mtfit/__init__.py
mtfit/_version.py
mtfit/inversion.py
mtfit/run.py
mtfit/sampling.py
mtfit/algorithms/__init__.py
mtfit/algorithms/base.py
mtfit/algorithms/cmarkov_chain_monte_carlo.c
mtfit/algorithms/cmarkov_chain_monte_carlo.cp36-win_amd64.pyd
mtfit/algorithms/cmarkov_chain_monte_carlo.pyx
mtfit/algorithms/markov_chain_monte_carlo.py
mtfit/algorithms/monte_carlo.py
mtfit/convert/__init__.py
mtfit/convert/cmoment_tensor_conversion.c
mtfit/convert/cmoment_tensor_conversion.cp36-win_amd64.pyd
mtfit/convert/cmoment_tensor_conversion.pxd
mtfit/convert/cmoment_tensor_conversion.pyx
mtfit/convert/moment_tensor_conversion.py
mtfit/extensions/__init__.py
mtfit/extensions/cscatangle.c
mtfit/extensions/cscatangle.cp36-win_amd64.pyd
mtfit/extensions/cscatangle.pyx
mtfit/extensions/scatangle.py
mtfit/extensions/example_parser/__init__.py
mtfit/extensions/example_parser/setup.py
mtfit/extensions/example_parser/test.txt
mtfit/extensions/model_sampling_strike_slip/__init__.py
mtfit/extensions/model_sampling_strike_slip/setup.py
mtfit/plot/__init__.py
mtfit/plot/core.py
mtfit/plot/plot_classes.py
mtfit/plot/spherical_projection.py
mtfit/probability/__init__.py
mtfit/probability/cprobability.c
mtfit/probability/cprobability.cp36-win_amd64.pyd
mtfit/probability/cprobability.pyx
mtfit/probability/probability.py
mtfit/tests/__init__.py
mtfit/tests/__main__.py
mtfit/tests/benchmarking.py
mtfit/tests/unit/__init__.py
mtfit/tests/unit/test_inversion.py
mtfit/tests/unit/test_run.py
mtfit/tests/unit/test_sampling.py
mtfit/tests/unit/algorithms/__init__.py
mtfit/tests/unit/algorithms/test_base.py
mtfit/tests/unit/algorithms/test_markov_chain_monte_carlo.py
mtfit/tests/unit/algorithms/test_monte_carlo.py
mtfit/tests/unit/convert/__init__.py
mtfit/tests/unit/convert/test_cmoment_tensor_conversion.py
mtfit/tests/unit/convert/test_moment_tensor_conversion.py
mtfit/tests/unit/extensions/__init__.py
mtfit-1.0.0.dist-info/DESCRIPTION.rst
mtfit-1.0.0.dist-info/METADATA
mtfit-1.0.0.dist-info/RECORD
mtfit-1.0.0.dist-info/WHEEL
mtfit-1.0.0.dist-info/entry_points.txt
mtfit-1.0.0.dist-info/metadata.json
mtfit-1.0.0.dist-info/top_level.txt
